{
    "name": "Cyberpunk 2077",
    "description": "Tema construído em torno do HUD do Cyberpunk 2077",
    "authors": [
        {
            "name": "Legend",
            "id": "498158678457843722"
        }
    ],
    "semanticColors": {
        "BACKGROUND_ACCENT": [
            "#ff003c"
        ],
        "BACKGROUND_MESSAGE_HOVER": [
            "#000000"
        ],
        "BACKGROUND_MOBILE_PRIMARY": [
            "#000000"
        ],
        "BACKGROUND_MOBILE_SECONDARY": [
            "#170005"
        ],
        "BACKGROUND_MODIFIER_ACCENT": [
            "#000000"
        ],
        "BACKGROUND_MODIFIER_ACTIVE": [
            "#170005"
        ],
        "BACKGROUND_MODIFIER_HOVER": [
            "#170005"
        ],
        "BACKGROUND_MODIFIER_SELECTED": [
            "#000000"
        ],
        "BACKGROUND_PRIMARY": [
            "#000000"
        ],
        "BACKGROUND_SECONDARY": [
            "#170005"
        ],
        "BACKGROUND_SECONDARY_ALT": [
            "#170005"
        ],
        "BACKGROUND_TERTIARY": [
            "#000000"
        ],
        "BORDER_FAINT": [
            "#ff003c"
        ],
        "BORDER_STRONG": [
            "#ff003c"
        ],
        "BORDER_SUBTLE": [
            "#ff003c"
        ],
        "CHANNEL_ICON": [
            "#ff003c"
        ],
        "CHANNELS_DEFAULT": [
            "#72eaf8"
        ],
        "CHAT_BACKGROUND": [
            "#000000"
        ],
        "HEADER_PRIMARY": [
            "#72eaf8"
        ],
        "HEADER_SECONDARY": [
            "#72eaf8"
        ],
        "HOME_BACKGROUND": [
            "#170005"
        ],
        "INTERACTIVE_ACTIVE": [
            "#f3e600"
        ],
        "INTERACTIVE_HOVER": [
            "#72eaf8"
        ],
        "INTERACTIVE_MUTED": [
            "#6e6a86"
        ],
        "INTERACTIVE_NORMAL": [
            "#7e5f5f"
        ],
        "REDESIGN_ACTIVITY_CARD_BACKGROUND": [
            "#000000"
        ],
        "SPOILER_HIDDEN_BACKGROUND": [
            "#120707"
        ],
        "TEXT_DANGER": [
            "#ff003c"
        ],
        "TEXT_LINK": [
            "#f3e600"
        ],
        "TEXT_MUTED": [
            "#ff003c"
        ],
        "TEXT_NORMAL": [
            "#c7c7c7"
        ],
        "TEXT_SECONDARY": [
            "#c7c7c7"
        ],
        "CARD_PRIMARY_BG": [
            "#000000"
        ],
        "CARD_SECONDARY_BG": [
            "#000000"
        ]
    },
    "rawColors": {
        "BRAND_260": "#f3e600",
        "BRAND_360": "#f3e600",
        "BRAND_500": "#f3e600",
        "GREEN_100": "#72eaf8",
        "GREEN_130": "#f3e600",
        "GREEN_160": "#f3e600",
        "GREEN_200": "#f3e600",
        "GREEN_230": "#f3e600",
        "GREEN_260": "#f3e600",
        "GREEN_300": "#f3e600",
        "GREEN_330": "#f3e600",
        "GREEN_345": "#f3e600",
        "GREEN_360": "#f3e600",
        "GREEN_400": "#f3e600",
        "GREEN_430": "#f3e600",
        "GREEN_460": "#f3e600",
        "GREEN_500": "#f3e600",
        "GREEN_530": "#f3e600",
        "GREEN_560": "#f3e600",
        "GREEN_600": "#f3e600",
        "GREEN_630": "#f3e600",
        "GREEN_660": "#f3e600",
        "GREEN_700": "#f3e600",
        "GREEN_730": "#f3e600",
        "GREEN_760": "#f3e600",
        "GREEN_800": "#f3e600",
        "GREEN_830": "#f3e600",
        "GREEN_860": "#f3e600",
        "GREEN_900": "#f3e600",
        "GUILD_BOOSTING_PINK": "#f3e600",
        "GUILD_BOOSTING_PURPLE": "#f3e600",
        "GUILD_BOOSTING_PURPLE_FOR_GRADIENTS": "#f3e600",
        "PRIMARY_100": "#610017",
        "PRIMARY_230": "#f3e600",
        "PRIMARY_300": "#72eaf8",
        "PRIMARY_360": "#72eaf8",
        "PRIMARY_400": "#72eaf8",
        "PRIMARY_460": "#000000",
        "PRIMARY_500": "#f3e600",
        "PRIMARY_600": "#000000",
        "PRIMARY_630": "#000000",
        "PRIMARY_660": "#000000",
        "PRIMARY_700": "#000000",
        "PRIMARY_800": "#000000",
        "RED_260": "#f3e600",
        "RED_300": "#f3e600",
        "RED_330": "#f3e600",
        "RED_345": "#f3e600",
        "RED_360": "#f3e600",
        "RED_400": "#f3e600",
        "RED_430": "#f3e600",
        "RED_460": "#f3e600",
        "RED_500": "#f3e600",
        "RED_530": "#f3e600",
        "RED_560": "#f3e600",
        "RED_600": "#f3e600",
        "RED_630": "#f3e600",
        "RED_660": "#f3e600",
        "RED_700": "#f3e600",
        "YELLOW_100": "#f3e600",
        "YELLOW_130": "#f3e600",
        "YELLOW_160": "#f3e600",
        "YELLOW_200": "#f3e600",
        "YELLOW_230": "#f3e600",
        "YELLOW_260": "#f3e600",
        "YELLOW_300": "#f3e600",
        "YELLOW_330": "#f3e600",
        "YELLOW_345": "#f3e600",
        "YELLOW_360": "#f3e600",
        "YELLOW_400": "#f3e600",
        "YELLOW_430": "#f3e600",
        "YELLOW_460": "#f3e600",
        "YELLOW_500": "#f3e600",
        "YELLOW_530": "#f3e600",
        "YELLOW_560": "#f3e600",
        "YELLOW_600": "#f3e600",
        "YELLOW_630": "#f3e600",
        "YELLOW_660": "#f3e600",
        "YELLOW_700": "#f3e600",
        "YELLOW_730": "#f3e600",
        "YELLOW_760": "#f3e600",
        "YELLOW_800": "#f3e600",
        "YELLOW_830": "#f3e600",
        "YELLOW_860": "#f3e600",
        "YELLOW_900": "#f3e600",
        "WHITE_500": "#c7c7c7",
        "PLUM_13": "#181818",
        "PLUM_15": "#170005",
        "PLUM_16": "#000000",
        "PLUM_17": "#170005",
        "PLUM_18": "#170005",
        "PLUM_19": "#000000",
        "PLUM_20": "#000000",
        "PLUM_22": "#000000",
        "PLUM_23": "#170005"
    },
    "background": {
        "blur": 0.1,
        "url": "https://raw.githubusercontent.com/olobia/themes/main/image%20(2).png",
        "alpha": 1.0
    },
    "spec": 2
}
